q/kv/__init__.py
q/kv/__init__.pyi
q/kv/api.py
q/kv/append.py
queue_kv-0.1.6.dist-info/METADATA
queue_kv-0.1.6.dist-info/WHEEL
queue_kv-0.1.6.dist-info/top_level.txt
queue_kv-0.1.6.dist-info/RECORD
