Metadata-Version: 2.1
Name: queue-kv
Version: 0.1.6
Summary: Queue implementation based on `kv.api`
Author-email: Marcel Claramunt <marcel@moveread.com>
Project-URL: repo, https://github.com/marciclabas/python-storage.git
Requires-Python: >=3.10
Requires-Dist: queue-api
Requires-Dist: kv-api
Requires-Dist: pydantic
Requires-Dist: lazy-loader
Provides-Extra: fs
Requires-Dist: kv-fs ; extra == 'fs'
Provides-Extra: sqlite
Requires-Dist: kv-sqlite-sync ; extra == 'sqlite'
